itypewriter/__init__.py
itypewriter/itypewriter.py
itypewriter-0.0.1.dist-info/LICENSE
itypewriter-0.0.1.dist-info/WHEEL
itypewriter-0.0.1.dist-info/METADATA
itypewriter-0.0.1.dist-info/RECORD
