Metadata-Version: 2.1
Name: itypewriter
Version: 0.0.1
Summary: iTypewriter - print text a character at a time,like typewriting.
Home-page: https://github.com/Jcharis/itypewriter
License: MIT
Keywords: iTypewriter,itypewriter,typewriter,typewrite,character a a time,chat,iterative chat,jcharistech,clean text,text preprocessing,text cleaning,ftfy,pandas,normalize
Author: Jesse E.Agbe(JCharis)
Author-email: jcharistech@gmail.com
Requires-Python: >=3.10,<4.0
Classifier: License :: OSI Approved :: MIT License
Classifier: Operating System :: OS Independent
Classifier: Programming Language :: Python :: 3
Classifier: Programming Language :: Python :: 3.10
Classifier: Programming Language :: Python :: 3.6
Classifier: Programming Language :: Python :: 3.7
Classifier: Programming Language :: Python :: 3.8
Classifier: Programming Language :: Python :: 3.9
Project-URL: Repository, https://github.com/Jcharis/itypewriter
